civilpy/CLI.py
civilpy/__init__.py
civilpy/construction/__init__.py
civilpy/environmental/__init__.py
civilpy/general/__init__.py
civilpy/general/database_tools.py
civilpy/general/jupyter.py
civilpy/general/photos.py
civilpy/general/bentley/__init__.py
civilpy/general/bentley/projectwise.py
civilpy/geotech/__init__.py
civilpy/geotech/culmanns.py
civilpy/state/__init__.py
civilpy/state/ohio/__init__.py
civilpy/state/ohio/db_tables.py
civilpy/state/ohio/search_tools.py
civilpy/state/ohio/snbi.py
civilpy/state/ohio/DOT/AssetWise.py
civilpy/state/ohio/DOT/D6_file_explorer.py
civilpy/state/ohio/DOT/ODOT_Inspection_Photo_DL.py
civilpy/state/ohio/DOT/OSE.py
civilpy/state/ohio/DOT/TIMS.py
civilpy/state/ohio/DOT/__init__.py
civilpy/state/ohio/DOT/aw_fields.py
civilpy/state/ohio/DOT/boring_logs.py
civilpy/state/ohio/DOT/bridge.py
civilpy/state/ohio/DOT/gemini.py
civilpy/state/ohio/DOT/legacy.py
civilpy/state/ohio/DOT/odot_concrete_slab_generator.py
civilpy/state/ohio/DOT/plan_splitter.py
civilpy/state/ohio/DOT/stage_2_comments.py
civilpy/state/ohio/DOT/title_sheet.py
civilpy/structural/__init__.py
civilpy/structural/beam_bending.py
civilpy/structural/midas.py
civilpy/structural/section_properties.py
civilpy/structural/steel.py
civilpy/structural/steel_db_temp.py
civilpy/structural/arema/__init__.py
civilpy/structural/arema/masonry.py
civilpy/structural/arema/rail_tpg_design.py
civilpy/structural/arema/steel.py
civilpy/structural/res/__init__.py
civilpy/structural/res/aisc_shapes_historic.csv
civilpy/structural/res/definitions.py
civilpy/structural/res/steel_shapes.csv
civilpy/transportation/__init__.py
civilpy/water_resources/__init__.py
civilpy/water_resources/hydraulics.py
civilpy-0.1.36.dist-info/licenses/LICENSE
civilpy-0.1.36.dist-info/METADATA
civilpy-0.1.36.dist-info/WHEEL
civilpy-0.1.36.dist-info/top_level.txt
civilpy-0.1.36.dist-info/RECORD
