Metadata-Version: 2.4
Name: civilpy
Version: 0.1.36
Summary: Civil Engineering Tools in Python
Home-page: https://daneparks.com/Dane/civilpy
Author: Dane Parks
Author-email: Dane@daneparks.com
License: AGPL-V3
Classifier: Development Status :: 4 - Beta
Classifier: Programming Language :: Python :: 3
Classifier: Programming Language :: Python :: 3.9
Classifier: Programming Language :: Python :: 3.10
Classifier: Programming Language :: Python :: 3.11
Classifier: Programming Language :: Python :: 3.12
Classifier: Programming Language :: Python :: 3.13
Classifier: Intended Audience :: Developers
Classifier: Natural Language :: English
Classifier: Operating System :: OS Independent
Classifier: Programming Language :: Python
Classifier: License :: OSI Approved :: GNU Affero General Public License v3 or later (AGPLv3+)
License-File: LICENSE
Requires-Dist: numpy>=2.0.2
Requires-Dist: folium>=0.12.1
Requires-Dist: pandas>=1.1.5
Requires-Dist: Pillow>=10.2.0
Requires-Dist: Pint>=0.12.2
Requires-Dist: coverage>=7.1.0
Requires-Dist: webdriver-manager>=3.8.5
Requires-Dist: msedge-selenium-tools>=3.141.4
Requires-Dist: Flask>=2.2.2
Requires-Dist: PyPDF2>=3.0.1
Requires-Dist: beautifulsoup4>=4.11.1
Requires-Dist: sympy>=1.10.0
Requires-Dist: sshtunnel>=0.4.0
Requires-Dist: termcolor>=1.1.0
Requires-Dist: icalendar>=4.0.7
Requires-Dist: html5lib>=1.1
Requires-Dist: geopandas>=0.6.2
Requires-Dist: fiona>=1.8.22
Requires-Dist: tifftools>=1.3.7
Requires-Dist: natsort>=8.2.0
Requires-Dist: html5lib>=1.1
Requires-Dist: requests>=2.28.2
Requires-Dist: pyntcloud>=0.3.1
Requires-Dist: openpyxl>=3.1.2
Requires-Dist: tqdm>=4.65.0
Requires-Dist: pytesseract>=0.3.10
Requires-Dist: pytest>=7.4.1
Provides-Extra: full
Requires-Dist: matplotlib>=3.6.3; extra == "full"
Requires-Dist: selenium>=3.141.0; extra == "full"
Requires-Dist: msedge-selenium-tools>=3.141.4; extra == "full"
Requires-Dist: jupyter>=1.0.0; extra == "full"
Requires-Dist: PyMuPDF>=1.23.7; extra == "full"
Requires-Dist: simplekml>=1.3.6; extra == "full"
Requires-Dist: psycopg2-binary>=2.9.5; extra == "full"
Requires-Dist: sympy>=1.10.0; extra == "full"
Requires-Dist: latex>=0.7.0; extra == "full"
Requires-Dist: laspy>=2.4.1; extra == "full"
Requires-Dist: earthpy>=0.9.4; extra == "full"
Requires-Dist: pymupdf>=1.22.3; extra == "full"
Requires-Dist: pyodbc>=4.0.39; extra == "full"
Requires-Dist: kivymd>=1.1.1; extra == "full"
Requires-Dist: PyQt5>=5.15.9; extra == "full"
Requires-Dist: tox>=4.11.1; extra == "full"
Requires-Dist: markdownify>=0.13.1; extra == "full"
Requires-Dist: pytest-cov>=4.1.0; extra == "full"
Dynamic: author
Dynamic: author-email
Dynamic: classifier
Dynamic: description
Dynamic: description-content-type
Dynamic: home-page
Dynamic: license
Dynamic: license-file
Dynamic: provides-extra
Dynamic: requires-dist
Dynamic: summary
